{
  "data": [
    {
      "ticker": "005930",
      "name": "삼성전자",
      "price": 101500,
      "change": 900,
      "change_rate": 0.89,
      "headline": "Nvidia와 AI 팩토리 구축 협력 소식. 3분기 실적 호조에 이어 AI 칩 수요 기대감 지속. 목표 주가 175,000원(최대) 전망."
    },
    {
      "ticker": "000660",
      "name": "SK하이닉스",
      "price": 578000,
      "change": -1000,
      "change_rate": -0.17,
      "headline": "AI 칩 수요에 힘입어 3분기 사상 최대 실적 달성. HBM 내년 물량까지 판매 완료되었으나, 단기 급등에 따른 숨 고르기."
    },
    {
      "ticker": "005380",
      "name": "현대차",
      "price": 312000,
      "change": 3000,
      "change_rate": 0.97,
      "headline": "美 10월 판매량 호조, 아이오닉 7 사전예약 기대. 4분기 배당 확대 정책 발표로 주주환원 기대감."
    },
    {
      "ticker": "207940",
      "name": "삼성바이오로직스",
      "price": 805000,
      "change": 5000,
      "change_rate": 0.63,
      "headline": "5공장 가동률 조기 달성, 4분기 수주 잭팟 기대. 글로벌 CDMO(위탁개발생산) 시장 지배력 강화."
    },
    {
      "ticker": "000270",
      "name": "기아",
      "price": 131000,
      "change": 1500,
      "change_rate": 1.16,
      "headline": "EV9 글로벌 판매 호조, 미국 시장 점유율 확대. 하이브리드 라인업 강화로 수익성 방어."
    },
    {
      "ticker": "068270",
      "name": "셀트리온",
      "price": 201000,
      "change": 2000,
      "change_rate": 1.01,
      "headline": "신약 '짐펜트라' 미국 시장 안착, 3분기 실적 서프라이즈. 합병 시너지 및 바이오시밀러 파이프라인 기대."
    }
  ]
}